pienex/__init__.py
pienex/pienex.py
pienex-0.1.0.dist-info/METADATA
pienex-0.1.0.dist-info/WHEEL
pienex-0.1.0.dist-info/top_level.txt
pienex-0.1.0.dist-info/RECORD
